ether/__init__.py
ether/_base_wallet.py
ether/async_wallet.py
ether/erc20.abi
ether/extras/__init__.py
ether/extras/defi.py
ether/extras/exceptions.py
ether/extras/tools.py
ether/types.py
ether/utils.py
ether/wallet.py
pyether-0.3.1.dist-info/LICENSE
pyether-0.3.1.dist-info/METADATA
pyether-0.3.1.dist-info/WHEEL
pyether-0.3.1.dist-info/RECORD
