Metadata-Version: 2.1
Name: pyether
Version: 0.3.1
Summary: The python package for interacting with Ethereum.
License: MIT
Keywords: web3,ethereum,ether.py,pyether,ether py,blockchain,web3.py,ethereum-python,eth,crypto,defi,dex
Author: Alexey
Author-email: axbelenkov@gmail.com
Requires-Python: >=3.9,<4.0
Classifier: Development Status :: 4 - Beta
Classifier: Intended Audience :: Developers
Classifier: License :: OSI Approved :: MIT License
Classifier: Operating System :: OS Independent
Classifier: Programming Language :: Python :: 3
Classifier: Programming Language :: Python :: 3.9
Classifier: Programming Language :: Python :: 3.10
Classifier: Programming Language :: Python :: 3.11
Classifier: Programming Language :: Python :: 3.12
Classifier: Programming Language :: Python :: 3 :: Only
Classifier: Topic :: Software Development :: Libraries :: Python Modules
Classifier: Typing :: Typed
Requires-Dist: pydantic (>=2.9.2,<3.0.0)
Requires-Dist: web3 (>=6.12.0,<7.0.0)
